kelvin/__init__.py
kelvin/cli.py
kelvin_track-0.1.0.dist-info/METADATA
kelvin_track-0.1.0.dist-info/WHEEL
kelvin_track-0.1.0.dist-info/entry_points.txt
kelvin_track-0.1.0.dist-info/RECORD
