Metadata-Version: 2.3
Name: kelvin-track
Version: 0.1.0
Summary: Add your description here
Requires-Python: >=3.12
Requires-Dist: rich>=13.9.1
